fastkit/__info__.py
fastkit/__init__.py
fastkit/cache/__init__.py
fastkit/cache/cacheout.py
fastkit/cache/redis.py
fastkit/configure/__init__.py
fastkit/database/__init__.py
fastkit/database/dataset.py
fastkit/database/mysql.py
fastkit/decorator/__init__.py
fastkit/decorator/decorator.py
fastkit/discovery/__init__.py
fastkit/executor/__init__.py
fastkit/executor/base.py
fastkit/executor/scheduler.py
fastkit/executor/thread_pool.py
fastkit/httpx/__init__.py
fastkit/httpx/httpclient.py
fastkit/httpx/status.py
fastkit/logging/__init__.py
fastkit/logging/local_log.py
fastkit/message/__init__.py
fastkit/message/kafka.py
fastkit/monitor/__init__.py
fastkit/utils/__init__.py
fastkit/utils/common.py
fastkit/utils/environ.py
fastkit/utils/format.py
fastkit/utils/ipaddress.py
fastkit/utils/scheduler.py
fastkit-0.1.22.dist-info/licenses/LICENSE
fastkit-0.1.22.dist-info/METADATA
fastkit-0.1.22.dist-info/WHEEL
fastkit-0.1.22.dist-info/top_level.txt
fastkit-0.1.22.dist-info/zip-safe
fastkit-0.1.22.dist-info/RECORD
