Metadata-Version: 2.4
Name: fastkit
Version: 0.1.22
Summary: FastKit — Python 开发工具包
Home-page: https://github.com/jagerzhang/fastkit.git
Author: Jagerzhang
Author-email: im@zhang.ge
License: Apache 2.0
Classifier: Programming Language :: Python :: 3
Requires-Python: >=3, <4
License-File: LICENSE
Requires-Dist: arrow==1.2.3
Requires-Dist: redis==3.5.3
Requires-Dist: kafka-python==2.0.2
Requires-Dist: pymysql<=1.1.0,>=0.10.0
Requires-Dist: dataset==1.6.2
Requires-Dist: apscheduler==3.10.4
Requires-Dist: httpx>=0.22.0
Requires-Dist: tenacity>=8.2.2
Requires-Dist: pyyaml>=6.0.1
Requires-Dist: cacheout>=0.14.0
Requires-Dist: redlock>=1.2.0
Dynamic: author
Dynamic: author-email
Dynamic: classifier
Dynamic: description
Dynamic: description-content-type
Dynamic: home-page
Dynamic: license
Dynamic: license-file
Dynamic: requires-dist
Dynamic: requires-python
Dynamic: summary
